[
  {
    "type": "updateEntity",
    "id": "a0eec9023f224fe498da69dbb616c99f",
    "set": [],
    "unset": [
      {
        "property": "a126ca530c8e48d5b88882c734c38935",
        "language": {
          "type": "all"
        }
      },
      {
        "property": "9b1f76ff9711404c861e59dc3fa7d037",
        "language": {
          "type": "all"
        }
      },
      {
        "property": "a126ca530c8e48d5b88882c734c38935",
        "language": {
          "type": "all"
        }
      },
      {
        "property": "9b1f76ff9711404c861e59dc3fa7d037",
        "language": {
          "type": "all"
        }
      },
      {
        "property": "91a9e2f6e51a48f7997661de8561b690",
        "language": {
          "type": "all"
        }
      },
      {
        "property": "94e43fe8faf241009eb887ab4f999723",
        "language": {
          "type": "all"
        }
      },
      {
        "property": "8b87530a67774d93a9aa8321b7f10019",
        "language": {
          "type": "all"
        }
      },
      {
        "property": "412ff593e9154012a43d4c27ec5c68b6",
        "language": {
          "type": "all"
        }
      },
      {
        "property": "1d274ed52372471289614a50168a37aa",
        "language": {
          "type": "all"
        }
      },
      {
        "property": "806d52bc27e94c9193c057978b093351",
        "language": {
          "type": "all"
        }
      },
      {
        "property": "5b722cd361d6494e88871310566437ba",
        "language": {
          "type": "all"
        }
      },
      {
        "property": "257090341ba5406f94e4d4af90042fba",
        "language": {
          "type": "all"
        }
      }
    ]
  },
  {
    "type": "updateEntity",
    "id": "dd909253d3f441b3bb09985f46fe4e1c",
    "set": [],
    "unset": [
      {
        "property": "a126ca530c8e48d5b88882c734c38935",
        "language": {
          "type": "all"
        }
      },
      {
        "property": "9b1f76ff9711404c861e59dc3fa7d037",
        "language": {
          "type": "all"
        }
      },
      {
        "property": "a126ca530c8e48d5b88882c734c38935",
        "language": {
          "type": "all"
        }
      },
      {
        "property": "9b1f76ff9711404c861e59dc3fa7d037",
        "language": {
          "type": "all"
        }
      },
      {
        "property": "91a9e2f6e51a48f7997661de8561b690",
        "language": {
          "type": "all"
        }
      },
      {
        "property": "94e43fe8faf241009eb887ab4f999723",
        "language": {
          "type": "all"
        }
      },
      {
        "property": "8b87530a67774d93a9aa8321b7f10019",
        "language": {
          "type": "all"
        }
      },
      {
        "property": "412ff593e9154012a43d4c27ec5c68b6",
        "language": {
          "type": "all"
        }
      },
      {
        "property": "1d274ed52372471289614a50168a37aa",
        "language": {
          "type": "all"
        }
      },
      {
        "property": "806d52bc27e94c9193c057978b093351",
        "language": {
          "type": "all"
        }
      },
      {
        "property": "5b722cd361d6494e88871310566437ba",
        "language": {
          "type": "all"
        }
      },
      {
        "property": "257090341ba5406f94e4d4af90042fba",
        "language": {
          "type": "all"
        }
      }
    ]
  },
  {
    "type": "deleteRelation",
    "id": "6e6df87c61454c91814829cc09eaa353"
  },
  {
    "type": "deleteRelation",
    "id": "6c730ac1b2024832bf3be471d62fa6a6"
  }
]